strictparent/__init__.py
strictparent/base.py
strictparent/tests.py
strictparent-3.3.2.dist-info/LICENSE
strictparent-3.3.2.dist-info/METADATA
strictparent-3.3.2.dist-info/WHEEL
strictparent-3.3.2.dist-info/top_level.txt
strictparent-3.3.2.dist-info/RECORD
