Metadata-Version: 2.1
Name: strictparent
Version: 3.3.2
Summary: @overrides and @final implementation for Python
Home-page: https://github.com/eeriksp/StrictParent
Author: Eerik Sven Puudist
Author-email: eerik@herbfoods.eu
License: UNKNOWN
Platform: UNKNOWN
Classifier: Programming Language :: Python :: 3
Classifier: License :: OSI Approved :: MIT License
Classifier: Operating System :: OS Independent
Classifier: Development Status :: 5 - Production/Stable
Classifier: Intended Audience :: Developers
Requires-Python: >=3.6
